.editorconfig
.gitignore
.readthedocs.yml
.travis.yml
AUTHORS.rst
CONTRIBUTING.rst
HISTORY.rst
LICENSE
MANIFEST.in
Makefile
README.rst
environment.yml
requirements.txt
requirements_dev.txt
setup.cfg
setup.py
tox.ini
.github/ISSUE_TEMPLATE.md
docs/Makefile
docs/authors.rst
docs/conf.py
docs/contributing.rst
docs/history.rst
docs/index.rst
docs/installation.rst
docs/make.bat
docs/modules.rst
docs/nb-rst.tpl
docs/pta_smbbh.rst
docs/readme.rst
docs/requirements.txt
docs/_build/html/_images/pta_smbbh_11_0.png
docs/_build/html/_images/pta_smbbh_12_0.png
docs/_build/html/_images/pta_smbbh_19_0.png
docs/_build/html/_images/pta_smbbh_19_1.png
docs/_build/html/_images/pta_smbbh_19_2.png
docs/_build/html/_images/pta_smbbh_19_3.png
docs/_build/html/_images/pta_smbbh_19_4.png
docs/_build/html/_images/pta_smbbh_19_5.png
docs/_build/html/_static/ajax-loader.gif
docs/_build/html/_static/comment-bright.png
docs/_build/html/_static/comment-close.png
docs/_build/html/_static/comment.png
docs/_build/html/_static/down-pressed.png
docs/_build/html/_static/down.png
docs/_build/html/_static/file.png
docs/_build/html/_static/minus.png
docs/_build/html/_static/plus.png
docs/_build/html/_static/up-pressed.png
docs/_build/html/_static/up.png
docs/_static/custom.css
docs/_static/notebooks/pta_smbbh.ipynb
docs/pta_smbbh_files/pta_smbbh_11_0.png
docs/pta_smbbh_files/pta_smbbh_12_0.png
docs/pta_smbbh_files/pta_smbbh_19_0.png
docs/pta_smbbh_files/pta_smbbh_19_1.png
docs/pta_smbbh_files/pta_smbbh_19_2.png
docs/pta_smbbh_files/pta_smbbh_19_3.png
docs/pta_smbbh_files/pta_smbbh_19_4.png
docs/pta_smbbh_files/pta_smbbh_19_5.png
gw_sky/__init__.py
gw_sky/gwsky.py
gw_sky.egg-info/PKG-INFO
gw_sky.egg-info/SOURCES.txt
gw_sky.egg-info/dependency_links.txt
gw_sky.egg-info/not-zip-safe
gw_sky.egg-info/requires.txt
gw_sky.egg-info/top_level.txt
gw_sky/data/smbbh_pop_gsmf.npz
tests/.coverage
tests/test_gw_sky.py
tests/test_notebooks.py