Metadata-Version: 1.1
Name: gw-sky
Version: 0.1.0
Summary: Python package for making visuals of gravitational wave signals, specifically pulsar timing array signals. 
Home-page: https://github.com/Hazboun6/gw_sky
Author: Jeffrey Shafiq Hazboun
Author-email: jeffrey.hazboun@gmail.com
License: MIT license
Keywords: gw_sky
Platform: UNKNOWN
Classifier: Development Status :: 2 - Pre-Alpha
Classifier: Intended Audience :: Developers
Classifier: License :: OSI Approved :: MIT License
Classifier: Natural Language :: English
Classifier: Programming Language :: Python :: 3
Classifier: Programming Language :: Python :: 3.4
Classifier: Programming Language :: Python :: 3.5
Classifier: Programming Language :: Python :: 3.6
Classifier: Programming Language :: Python :: 3.7
